README.md
setup.py
PanelApp_client_API.egg-info/PKG-INFO
PanelApp_client_API.egg-info/SOURCES.txt
PanelApp_client_API.egg-info/dependency_links.txt
PanelApp_client_API.egg-info/requires.txt
PanelApp_client_API.egg-info/top_level.txt
panel_app_query/__init__.py
panel_app_query/basic.py
panel_app_query/pandas.py
panel_app_query/parsed.py