Metadata-Version: 2.1
Name: PanelApp-client-API
Version: 0.1
Summary: unofficial Python3 client API (SDK) for Genomics England (GEL) PanelApp
Home-page: https://github.com/matteoferla/PanelApp_Python3_client_API
Author: Matteo Ferla
Author-email: matteo.ferla@gmail.com
License: MIT
Platform: UNKNOWN
